Workbook

Sheet Cover
A1: Collab: Sales × Media – UAT test script
A2: Persona | B2: Agency media planner
A3: Environment | B3: Beta – https://collab-media-production-945a.up.railway.app/home
A4: Version | B4: v0.1 draft for stakeholder review
A5: Prepared by | B5: QA lead
A6: Date | B6: 11 Oct 2026
A7: Scope | B7: Sign-in and Home; client brief intake; AI brief scoring; media plan builder; budget calculations; AI pitch generation; knowledge bank; review and approval; usability and non-functional checks; one end-to-end journey.
A8: Out of scope | B8: Collab: Influence, Studio and Content pillars; platform admin features; load and security penetration testing.
A9: Basis | B9: Test cases come from the Collabrium Mothership architecture spec and capability architecture (Media & Campaign and Sales pillar capabilities). Before the test cycle starts, the QA lead must check each case against the beta screens in a dry run. Cases for features the beta does not have yet should be marked 'N/A – not in build'.
A10: Entry criteria | B10: Beta build deployed and stable; test accounts issued (media planner and approver); current rate card loaded; test client data seeded in the sandbox (no production data).
A11: Exit criteria | B11: 100% of High-priority cases run; 0 open Critical or High defects; Medium defects have an agreed fix plan; business sign-off recorded on the Sign-off tab.
A12: How to use | B12: 1. Work through the 'Test cases' tab in order (TC IDs are grouped by module). 2. Follow the steps and use the test data given. 3. Fill in the yellow columns only: Actual result, Status, Defect ID, Tester, Date tested and Comments. 4. Status options: Pass / Fail / Blocked / Not run / N/A. 5. For every Fail or Blocked case, log a defect on the 'Defect log' tab, then put its ID in the test case. Attach a screenshot. 6. The 'Summary' tab updates automatically.
A13: Example of a completed row | B13: Actual result: 'Impressions showed 2,000,000.' Status: Pass. Defect ID: (blank). Tester: A. Tan. Date tested: 20 Oct 2026. Example of a Fail: Actual result: 'Total showed RM 249,999.98, 2 sen short.' Status: Fail. Defect ID: DEF-001.
A14: Severity guide | B14: Critical – blocks the planner's core work, causes data loss or wrong money figures. High – a major feature is broken and there is no reasonable workaround. Medium – a feature is impaired but a workaround exists. Low – cosmetic or wording issue.

Sheet Test cases
A1: TC ID | B1: Module | C1: Test scenario | D1: Priority | E1: Preconditions | F1: Test steps | G1: Test data | H1: Expected result | I1: Actual result | J1: Status | K1: Defect ID | L1: Tester | M1: Date tested | N1: Comments / planner feedback
A2: ACC-01 | B2: 01 Access & Home | C2: Sign in with corporate SSO credentials | D2: High | E2: Tester has an active media planner account. | F2: 1. Open the beta link in Chrome. 2. Click sign in. 3. Enter corporate credentials and complete MFA if prompted. | G2: Media planner test account | H2: Sign-in succeeds and the tester lands on Collab: Home. Their name and role show correctly. | J2: Not run
A3: ACC-02 | B3: 01 Access & Home | C3: Home shows only the pillars a media planner can access | D3: High | E3: Signed in as a media planner. | F3: 1. Review the pillars and tiles on Home. 2. Compare them with the role matrix for a media planner. | G3: Role matrix from the product team | H3: Collab: Sales × Media is visible. Pillars the role does not grant (e.g. Studio admin and platform admin) are hidden, not just disabled. | J3: Not run
A4: ACC-03 | B4: 01 Access & Home | C4: Navigate from Home into Collab: Sales × Media | D4: High | E4: Signed in. | F4: 1. On Home, click Sales × Media. 2. Check the sidebar menu items. | G4: — | H4: The pillar opens without a second login. The sidebar lists media planning, brief intake, pitch generation and knowledge bank. | J4: Not run
A5: ACC-04 | B5: 01 Access & Home | C5: Block direct URL access to an unpermitted pillar | D5: High | E5: Signed in as a media planner. | F5: 1. Paste the URL of a pillar or admin page the role does not grant (ask the QA lead for it). 2. Press Enter. | G5: Admin or other pillar URL | H5: Access is denied with a clear message and a way back to Home. No data from that pillar is shown. | J5: Not run
A6: ACC-05 | B6: 01 Access & Home | C6: Invalid credentials are rejected | D6: Medium | E6: Signed out. | F6: 1. Attempt to sign in with a wrong password. | G6: Wrong password | H6: Sign-in fails with a clear, non-technical error. No account details are revealed. | J6: Not run
A7: ACC-06 | B7: 01 Access & Home | C7: Sign out and session expiry | D7: Medium | E7: Signed in. | F7: 1. Click sign out. 2. Press the browser Back button. 3. Sign in again, leave the tab idle past the session timeout, then click any link. | G7: Session timeout value from the product team | H7: After sign-out, Back does not reveal pages. After the timeout, the tester is asked to sign in again. Unsaved work is either kept or the tester is warned first. | J7: Not run
A8: BRF-01 | B8: 02 Client brief intake | C8: Create a new client brief with all required fields | D8: High | E8: Signed in to Sales × Media. | F8: 1. Go to brief intake and click to create a new brief. 2. Fill every required field from the test data. 3. Save. | G8: Client: Kopi Kita Sdn Bhd (UAT test client) Kopi Kita CNY 2027 awareness campaign; Objective: awareness + store visits; Budget RM 250,000; Flight 1 Dec 2026 – 31 Jan 2027; Audience: Adults 25–44, Klang Valley, coffee drinkers; KPIs: 10M impressions, 2M video views | H8: The brief is saved with status Draft. The planner is shown as owner. All values display exactly as entered. | J8: Not run
A9: BRF-02 | B9: 02 Client brief intake | C9: Required-field validation on brief | D9: High | E9: On the new brief form. | F9: 1. Leave client name, budget and flight dates empty. 2. Try to save or submit. | G9: Blank required fields | H9: Saving or submitting is blocked. Each missing field is flagged inline with a clear message. | J9: Not run
A10: BRF-03 | B10: 02 Client brief intake | C10: Invalid budget and date input | D10: High | E10: On the new brief form. | F10: 1. Enter a budget of -5000, then 'abc'. 2. Enter an end date earlier than the start date. | G10: Budget: -5000 / abc; Flight 31 Jan 2027 – 1 Dec 2026 | H10: Negative and non-numeric budgets are rejected. An end date before the start date is rejected. The error messages say how to fix the input. | J10: Not run
A11: BRF-04 | B11: 02 Client brief intake | C11: Currency formatting in RM | D11: Medium | E11: Brief saved. | F11: 1. Enter budget 250000. 2. Save and view the brief. | G11: 250000 | H11: The budget displays as RM 250,000 (space after RM, comma thousands). | J11: Not run
A12: BRF-05 | B12: 02 Client brief intake | C12: Attach a client brief document | D12: Medium | E12: Brief in Draft. | F12: 1. Upload the client's PDF brief and a PPTX reference deck. 2. Try to upload an unsupported file (e.g. .exe) and an oversized file. | G12: Sample PDF (≤10 MB), PPTX, .exe, a file larger than the upload limit | H12: PDF and PPTX upload and can be opened or downloaded. The unsupported and oversized files are rejected with a clear reason. | J12: Not run
A13: BRF-06 | B13: 02 Client brief intake | C13: Edit a draft brief and view its history | D13: Medium | E13: Brief in Draft. | F13: 1. Change the budget to RM 300,000 and save. 2. Open version history, if available. | G13: RM 300,000 | H13: The change is saved. The history shows the earlier value, who changed it and when. | J13: Not run
... A58: E2E-01 | B58: 10 End-to-end journey | C58: Full planner journey: brief to approved plan to pitch | D58: High | E58: All modules available; planner and approver accounts. | F58: 1. Sign in, open Sales × Media. 2. Create and submit the Kopi Kita brief and score it. 3. Build a plan with 5 or more channels within RM 250,000. 4. Use the AI assistant once. 5. Submit for approval, get approved. 6. Generate, approve and download the pitch. 7. Export the plan to Excel. | G58: Client: Kopi Kita Sdn Bhd (UAT test client) Kopi Kita CNY 2027 awareness campaign; Objective: awareness + store visits; Budget RM 250,000; Flight 1 Dec 2026 – 31 Jan 2027; Audience: Adults 25–44, Klang Valley, coffee drinkers; KPIs: 10M impressions, 2M video views | H58: The journey completes with no blockers. The data is consistent across brief, plan, pitch and exports. The planner rates the overall experience 1–5 in comments. | J58: Not run

Sheet Defect log
A1: Defect ID | B1: Related TC ID | C1: Title | D1: Severity | E1: Steps to reproduce | F1: Expected | G1: Actual | H1: Screenshot / link | I1: Browser | J1: Raised by | K1: Date raised | L1: Owner | M1: Status | N1: Resolution notes
A2: DEF-001
A3: DEF-002
A4: DEF-003
A5: DEF-004
A6: DEF-005
A7: DEF-006
A8: DEF-007
A9: DEF-008
A10: DEF-009
A11: DEF-010
A12: DEF-011
A13: DEF-012
... A101: DEF-100

Sheet Summary
A1: Module | B1: Total | C1: Pass | D1: Fail | E1: Blocked | F1: Not run | G1: N/A | H1: Executed % | I1: Pass rate %
A2: 01 Access & Home | B2: =COUNTIF('Test cases'!$B$2:$B$58,A2) -> 6 | C2: =COUNTIFS('Test cases'!$B$2:$B$58,$A2,'Test cases'!$J$2:$J$58,"Pass") -> 0 | D2: =COUNTIFS('Test cases'!$B$2:$B$58,$A2,'Test cases'!$J$2:$J$58,"Fail") -> 0 | E2: =COUNTIFS('Test cases'!$B$2:$B$58,$A2,'Test cases'!$J$2:$J$58,"Blocked") -> 0 | F2: =COUNTIFS('Test cases'!$B$2:$B$58,$A2,'Test cases'!$J$2:$J$58,"Not run") -> 6 | G2: =COUNTIFS('Test cases'!$B$2:$B$58,$A2,'Test cases'!$J$2:$J$58,"N/A") -> 0 | H2: =IF((B2-G2)=0,0,(C2+D2+E2)/(B2-G2)) -> 0 | I2: =IF((C2+D2)=0,0,C2/(C2+D2)) -> 0
A3: 02 Client brief intake | B3: =COUNTIF('Test cases'!$B$2:$B$58,A3) -> 8 | C3: =COUNTIFS('Test cases'!$B$2:$B$58,$A3,'Test cases'!$J$2:$J$58,"Pass") -> 0 | D3: =COUNTIFS('Test cases'!$B$2:$B$58,$A3,'Test cases'!$J$2:$J$58,"Fail") -> 0 | E3: =COUNTIFS('Test cases'!$B$2:$B$58,$A3,'Test cases'!$J$2:$J$58,"Blocked") -> 0 | F3: =COUNTIFS('Test cases'!$B$2:$B$58,$A3,'Test cases'!$J$2:$J$58,"Not run") -> 8 | G3: =COUNTIFS('Test cases'!$B$2:$B$58,$A3,'Test cases'!$J$2:$J$58,"N/A") -> 0 | H3: =IF((B3-G3)=0,0,(C3+D3+E3)/(B3-G3)) -> 0 | I3: =IF((C3+D3)=0,0,C3/(C3+D3)) -> 0
A4: 03 Brief scoring (AI) | B4: =COUNTIF('Test cases'!$B$2:$B$58,A4) -> 4 | C4: =COUNTIFS('Test cases'!$B$2:$B$58,$A4,'Test cases'!$J$2:$J$58,"Pass") -> 0 | D4: =COUNTIFS('Test cases'!$B$2:$B$58,$A4,'Test cases'!$J$2:$J$58,"Fail") -> 0 | E4: =COUNTIFS('Test cases'!$B$2:$B$58,$A4,'Test cases'!$J$2:$J$58,"Blocked") -> 0 | F4: =COUNTIFS('Test cases'!$B$2:$B$58,$A4,'Test cases'!$J$2:$J$58,"Not run") -> 4 | G4: =COUNTIFS('Test cases'!$B$2:$B$58,$A4,'Test cases'!$J$2:$J$58,"N/A") -> 0 | H4: =IF((B4-G4)=0,0,(C4+D4+E4)/(B4-G4)) -> 0 | I4: =IF((C4+D4)=0,0,C4/(C4+D4)) -> 0
A5: 04 Media plan builder | B5: =COUNTIF('Test cases'!$B$2:$B$58,A5) -> 11 | C5: =COUNTIFS('Test cases'!$B$2:$B$58,$A5,'Test cases'!$J$2:$J$58,"Pass") -> 0 | D5: =COUNTIFS('Test cases'!$B$2:$B$58,$A5,'Test cases'!$J$2:$J$58,"Fail") -> 0 | E5: =COUNTIFS('Test cases'!$B$2:$B$58,$A5,'Test cases'!$J$2:$J$58,"Blocked") -> 0 | F5: =COUNTIFS('Test cases'!$B$2:$B$58,$A5,'Test cases'!$J$2:$J$58,"Not run") -> 11 | G5: =COUNTIFS('Test cases'!$B$2:$B$58,$A5,'Test cases'!$J$2:$J$58,"N/A") -> 0 | H5: =IF((B5-G5)=0,0,(C5+D5+E5)/(B5-G5)) -> 0 | I5: =IF((C5+D5)=0,0,C5/(C5+D5)) -> 0
A6: 05 Budget & calculations | B6: =COUNTIF('Test cases'!$B$2:$B$58,A6) -> 6 | C6: =COUNTIFS('Test cases'!$B$2:$B$58,$A6,'Test cases'!$J$2:$J$58,"Pass") -> 0 | D6: =COUNTIFS('Test cases'!$B$2:$B$58,$A6,'Test cases'!$J$2:$J$58,"Fail") -> 0 | E6: =COUNTIFS('Test cases'!$B$2:$B$58,$A6,'Test cases'!$J$2:$J$58,"Blocked") -> 0 | F6: =COUNTIFS('Test cases'!$B$2:$B$58,$A6,'Test cases'!$J$2:$J$58,"Not run") -> 6 | G6: =COUNTIFS('Test cases'!$B$2:$B$58,$A6,'Test cases'!$J$2:$J$58,"N/A") -> 0 | H6: =IF((B6-G6)=0,0,(C6+D6+E6)/(B6-G6)) -> 0 | I6: =IF((C6+D6)=0,0,C6/(C6+D6)) -> 0
A7: 06 Pitch generation (AI) | B7: =COUNTIF('Test cases'!$B$2:$B$58,A7) -> 6 | C7: =COUNTIFS('Test cases'!$B$2:$B$58,$A7,'Test cases'!$J$2:$J$58,"Pass") -> 0 | D7: =COUNTIFS('Test cases'!$B$2:$B$58,$A7,'Test cases'!$J$2:$J$58,"Fail") -> 0 | E7: =COUNTIFS('Test cases'!$B$2:$B$58,$A7,'Test cases'!$J$2:$J$58,"Blocked") -> 0 | F7: =COUNTIFS('Test cases'!$B$2:$B$58,$A7,'Test cases'!$J$2:$J$58,"Not run") -> 6 | G7: =COUNTIFS('Test cases'!$B$2:$B$58,$A7,'Test cases'!$J$2:$J$58,"N/A") -> 0 | H7: =IF((B7-G7)=0,0,(C7+D7+E7)/(B7-G7)) -> 0 | I7: =IF((C7+D7)=0,0,C7/(C7+D7)) -> 0
A8: 07 Knowledge bank | B8: =COUNTIF('Test cases'!$B$2:$B$58,A8) -> 4 | C8: =COUNTIFS('Test cases'!$B$2:$B$58,$A8,'Test cases'!$J$2:$J$58,"Pass") -> 0 | D8: =COUNTIFS('Test cases'!$B$2:$B$58,$A8,'Test cases'!$J$2:$J$58,"Fail") -> 0 | E8: =COUNTIFS('Test cases'!$B$2:$B$58,$A8,'Test cases'!$J$2:$J$58,"Blocked") -> 0 | F8: =COUNTIFS('Test cases'!$B$2:$B$58,$A8,'Test cases'!$J$2:$J$58,"Not run") -> 4 | G8: =COUNTIFS('Test cases'!$B$2:$B$58,$A8,'Test cases'!$J$2:$J$58,"N/A") -> 0 | H8: =IF((B8-G8)=0,0,(C8+D8+E8)/(B8-G8)) -> 0 | I8: =IF((C8+D8)=0,0,C8/(C8+D8)) -> 0
A9: 08 Review, approval & collaboration | B9: =COUNTIF('Test cases'!$B$2:$B$58,A9) -> 6 | C9: =COUNTIFS('Test cases'!$B$2:$B$58,$A9,'Test cases'!$J$2:$J$58,"Pass") -> 0 | D9: =COUNTIFS('Test cases'!$B$2:$B$58,$A9,'Test cases'!$J$2:$J$58,"Fail") -> 0 | E9: =COUNTIFS('Test cases'!$B$2:$B$58,$A9,'Test cases'!$J$2:$J$58,"Blocked") -> 0 | F9: =COUNTIFS('Test cases'!$B$2:$B$58,$A9,'Test cases'!$J$2:$J$58,"Not run") -> 6 | G9: =COUNTIFS('Test cases'!$B$2:$B$58,$A9,'Test cases'!$J$2:$J$58,"N/A") -> 0 | H9: =IF((B9-G9)=0,0,(C9+D9+E9)/(B9-G9)) -> 0 | I9: =IF((C9+D9)=0,0,C9/(C9+D9)) -> 0
A10: 09 Usability & non-functional | B10: =COUNTIF('Test cases'!$B$2:$B$58,A10) -> 5 | C10: =COUNTIFS('Test cases'!$B$2:$B$58,$A10,'Test cases'!$J$2:$J$58,"Pass") -> 0 | D10: =COUNTIFS('Test cases'!$B$2:$B$58,$A10,'Test cases'!$J$2:$J$58,"Fail") -> 0 | E10: =COUNTIFS('Test cases'!$B$2:$B$58,$A10,'Test cases'!$J$2:$J$58,"Blocked") -> 0 | F10: =COUNTIFS('Test cases'!$B$2:$B$58,$A10,'Test cases'!$J$2:$J$58,"Not run") -> 5 | G10: =COUNTIFS('Test cases'!$B$2:$B$58,$A10,'Test cases'!$J$2:$J$58,"N/A") -> 0 | H10: =IF((B10-G10)=0,0,(C10+D10+E10)/(B10-G10)) -> 0 | I10: =IF((C10+D10)=0,0,C10/(C10+D10)) -> 0
A11: 10 End-to-end journey | B11: =COUNTIF('Test cases'!$B$2:$B$58,A11) -> 1 | C11: =COUNTIFS('Test cases'!$B$2:$B$58,$A11,'Test cases'!$J$2:$J$58,"Pass") -> 0 | D11: =COUNTIFS('Test cases'!$B$2:$B$58,$A11,'Test cases'!$J$2:$J$58,"Fail") -> 0 | E11: =COUNTIFS('Test cases'!$B$2:$B$58,$A11,'Test cases'!$J$2:$J$58,"Blocked") -> 0 | F11: =COUNTIFS('Test cases'!$B$2:$B$58,$A11,'Test cases'!$J$2:$J$58,"Not run") -> 1 | G11: =COUNTIFS('Test cases'!$B$2:$B$58,$A11,'Test cases'!$J$2:$J$58,"N/A") -> 0 | H11: =IF((B11-G11)=0,0,(C11+D11+E11)/(B11-G11)) -> 0 | I11: =IF((C11+D11)=0,0,C11/(C11+D11)) -> 0
A12: Total | B12: =SUM(B2:B11) -> 57 | C12: =SUM(C2:C11) -> 0 | D12: =SUM(D2:D11) -> 0 | E12: =SUM(E2:E11) -> 0 | F12: =SUM(F2:F11) -> 57 | G12: =SUM(G2:G11) -> 0 | H12: =IF((B12-G12)=0,0,(C12+D12+E12)/(B12-G12)) -> 0 | I12: =IF((C12+D12)=0,0,C12/(C12+D12)) -> 0
A14: High-priority cases
A15: Total High | B15: =COUNTIF('Test cases'!$D$2:$D$58,"High") -> 34
A16: High executed | B16: =COUNTIFS('Test cases'!$D$2:$D$58,"High",'Test cases'!$J$2:$J$58,"Pass")+COUNTIFS('Test cases'!$D$2:$D$58,"High",'Test cases'!$J$2:$J$58,"Fail")+COUNTIFS('Test cases'!$D$2:$D$58,"High",'Test cases'!$J$2:$J$58,"Blocked") -> 0
A17: High executed % | B17: =IF(B15=0,0,B16/B15) -> 0
A19: Open defects by severity (status not Closed or Rejected)
A20: Critical | B20: =COUNTIFS('Defect log'!$D$2:$D$101,"Critical",'Defect log'!$M$2:$M$101,"<>Closed",'Defect log'!$M$2:$M$101,"<>Rejected") -> 0
A21: High | B21: =COUNTIFS('Defect log'!$D$2:$D$101,"High",'Defect log'!$M$2:$M$101,"<>Closed",'Defect log'!$M$2:$M$101,"<>Rejected") -> 0
A22: Medium | B22: =COUNTIFS('Defect log'!$D$2:$D$101,"Medium",'Defect log'!$M$2:$M$101,"<>Closed",'Defect log'!$M$2:$M$101,"<>Rejected") -> 0
A23: Low | B23: =COUNTIFS('Defect log'!$D$2:$D$101,"Low",'Defect log'!$M$2:$M$101,"<>Closed",'Defect log'!$M$2:$M$101,"<>Rejected") -> 0
A25: Exit criteria met? | B25: =IF(AND(B17=1,B20=0,B21=0),"Yes","No") -> No
A26: Exit rule: all High-priority cases executed and no open Critical or High defects (see Cover).

Sheet Sign-off
A1: Role | B1: Name | C1: Decision (Accept / Accept with conditions / Reject) | D1: Conditions or comments | E1: Signature | F1: Date
A2: Business owner – Sales × Media
A3: Lead media planner
A4: Product owner
A5: QA lead
A6: Platform / engineering lead
